knives/__init__.py
knives/exception.py
knives/measure.py
knives/pathlib.py
knives/timer.py
knives-0.0.3.dist-info/METADATA
knives-0.0.3.dist-info/WHEEL
knives-0.0.3.dist-info/top_level.txt
knives-0.0.3.dist-info/RECORD
