Metadata-Version: 2.1
Name: knives
Version: 0.0.3
Summary: A commonly used python tools library for myself
Home-page: https://github.com/owtotwo/knives
Author: owtotwo
Author-email: owtotwo@163.com
License: UNKNOWN
Platform: UNKNOWN
Classifier: Programming Language :: Python :: 3 :: Only
Classifier: License :: OSI Approved :: GNU Lesser General Public License v3 (LGPLv3)
Classifier: Operating System :: Microsoft :: Windows :: Windows 10
Requires-Python: >=3.7
